pyplastimatch/__init__.py
pyplastimatch/pyplastimatch.py
pyplastimatch/utils/__init__.py
pyplastimatch/utils/data.py
pyplastimatch/utils/eval.py
pyplastimatch/utils/install.py
pyplastimatch/utils/widgets.py
pyplastimatch-0.4.6.dist-info/LICENSE
pyplastimatch-0.4.6.dist-info/METADATA
pyplastimatch-0.4.6.dist-info/WHEEL
pyplastimatch-0.4.6.dist-info/top_level.txt
pyplastimatch-0.4.6.dist-info/RECORD
