Metadata-Version: 2.1
Name: pyplastimatch
Version: 0.4.6
Summary: Basic Python wrapper for Plastimatch
Home-page: https://github.com/ImagingDataCommons/pyplastimatch
Author: Dennis Bontempi
Author-email: Dennis Bontempi <dbontempi@bwh.harvard.edu>, Leonard Nuernberg <lnuernberg@bwh.harvard.edu>
Maintainer-email: Dennis Bontempi <dbontempi@bwh.harvard.edu>, Leonard Nuernberg <lnuernberg@bwh.harvard.edu>, Andrey Fedorov <andrey.fedorov@gmail.com>
License: Copyright 2022 Imaging Data Commons
Project-URL: Homepage, https://github.com/ImagingDataCommons/pyplastimatch
Project-URL: Bug Tracker, https://github.com/ImagingDataCommons/pyplastimatch/issues
Classifier: Programming Language :: Python :: 3
Classifier: Operating System :: POSIX :: Linux
Requires-Python: >=3.7
License-File: LICENSE
Requires-Dist: itk
Requires-Dist: matplotlib
Requires-Dist: numpy
Requires-Dist: pandas
Requires-Dist: pydicom
Requires-Dist: requests
Requires-Dist: scikit-image
Requires-Dist: SimpleITK
